<annotation>
	<folder>bPawn</folder>
	<filename>bPawn46.jpg</filename>
	<path>/home/justin/Desktop/chess/bPawn/bPawn46.jpg</path>
	<source>
		<database>Unknown</database>
	</source>
	<size>
		<width>300</width>
		<height>300</height>
		<depth>3</depth>
	</size>
	<segmented>0</segmented>
	<object>
		<name>bPawn</name>
		<pose>Unspecified</pose>
		<truncated>1</truncated>
		<difficult>0</difficult>
		<bndbox>
			<xmin>141</xmin>
			<ymin>69</ymin>
			<xmax>199</xmax>
			<ymax>300</ymax>
		</bndbox>
	</object>
	<object>
		<name>bPawn</name>
		<pose>Unspecified</pose>
		<truncated>1</truncated>
		<difficult>0</difficult>
		<bndbox>
			<xmin>27</xmin>
			<ymin>54</ymin>
			<xmax>84</xmax>
			<ymax>300</ymax>
		</bndbox>
	</object>
</annotation>
