<annotation>
	<folder>train</folder>
	<filename>bPawn52.jpg</filename>
	<path>/home/justin/Desktop/chess/images/train/bPawn52.jpg</path>
	<source>
		<database>Unknown</database>
	</source>
	<size>
		<width>300</width>
		<height>300</height>
		<depth>3</depth>
	</size>
	<segmented>0</segmented>
	<object>
		<name>bPawn</name>
		<pose>Unspecified</pose>
		<truncated>0</truncated>
		<difficult>0</difficult>
		<bndbox>
			<xmin>139</xmin>
			<ymin>69</ymin>
			<xmax>170</xmax>
			<ymax>140</ymax>
		</bndbox>
	</object>
	<object>
		<name>bPawn</name>
		<pose>Unspecified</pose>
		<truncated>0</truncated>
		<difficult>0</difficult>
		<bndbox>
			<xmin>141</xmin>
			<ymin>102</ymin>
			<xmax>174</xmax>
			<ymax>182</ymax>
		</bndbox>
	</object>
	<object>
		<name>wPawn</name>
		<pose>Unspecified</pose>
		<truncated>0</truncated>
		<difficult>0</difficult>
		<bndbox>
			<xmin>124</xmin>
			<ymin>12</ymin>
			<xmax>150</xmax>
			<ymax>67</ymax>
		</bndbox>
	</object>
	<object>
		<name>wPawn</name>
		<pose>Unspecified</pose>
		<truncated>0</truncated>
		<difficult>0</difficult>
		<bndbox>
			<xmin>194</xmin>
			<ymin>99</ymin>
			<xmax>233</xmax>
			<ymax>182</ymax>
		</bndbox>
	</object>
	<object>
		<name>wPawn</name>
		<pose>Unspecified</pose>
		<truncated>0</truncated>
		<difficult>0</difficult>
		<bndbox>
			<xmin>31</xmin>
			<ymin>137</ymin>
			<xmax>73</xmax>
			<ymax>230</ymax>
		</bndbox>
	</object>
</annotation>
